{
  "symbol": "JINDALPHOT",
  "label": "JINDALPHOT - JINDAL PHOTO LTD. - CONSUMER DURABLES - INDIA",
  "BalanceSheet": [
    {
      "Date": "Mar-24",
      "Total Stockholders Fund": "2260.58",
      "Minority Interest": "-265.55",
      "Total Non Current Liabilities": "0.0100",
      "Total Current Liabilities": "73.96",
      "Total Liabilities": "73.97",
      "Liabilities & Sh Holder Eq": "2334.55",
      "Total Non Current Assets": "4.56",
      "Total Current Assets": "2329.99",
      "Total Assets": "2334.55",
      "Net Working Capital": "6.44",
      "Net Invested Capital": "2315.11",
      "Common Share Oustanding": "1.03",
      "Book Value / Share": "2203.63"
    },
    {
      "Date": "Mar-23",
      "Total Stockholders Fund": "1992.47",
      "Minority Interest": "0",
      "Total Non Current Liabilities": "87.76",
      "Total Current Liabilities": "19.45",
      "Total Liabilities": "87.76",
      "Liabilities & Sh Holder Eq": "2080.23",
      "Total Non Current Assets": "2073.80",
      "Total Current Assets": "6.43",
      "Total Assets": "2080.23",
      "Net Working Capital": "38.31",
      "Net Invested Capital": "2060.75",
      "Common Share Oustanding": "1.03",
      "Book Value / Share": "1942.30"
    },
    {
      "Date": "Mar-22",
      "Total Stockholders Fund": "1824.74",
      "Minority Interest": "-637.76",
      "Total Non Current Liabilities": "1.19",
      "Total Current Liabilities": "82.08",
      "Total Liabilities": "83.27",
      "Liabilities & Sh Holder Eq": "0",
      "Total Non Current Assets": "4.65",
      "Total Current Assets": "1903.36",
      "Total Assets": "1908.01",
      "Net Working Capital": "1821.28",
      "Net Invested Capital": "1887.38",
      "Common Share Oustanding": "1.03",
      "Book Value / Share": "1778.79"
    },
    {
      "Date": "Mar-21",
      "Total Stockholders Fund": "25.01",
      "Minority Interest": "0.050",
      "Total Non Current Liabilities": "3.54",
      "Total Current Liabilities": "76.92",
      "Total Liabilities": "80.46",
      "Liabilities & Sh Holder Eq": "0",
      "Total Non Current Assets": "4.57",
      "Total Current Assets": "100.90",
      "Total Assets": "105.47",
      "Net Working Capital": "23.98",
      "Net Invested Capital": "82.48",
      "Common Share Oustanding": "1.03",
      "Book Value / Share": "24.38"
    },
    {
      "Date": "Mar-20",
      "Total Stockholders Fund": "24.23",
      "Minority Interest": "0",
      "Total Non Current Liabilities": "54.94",
      "Total Current Liabilities": "19.44",
      "Total Liabilities": "74.38",
      "Liabilities & Sh Holder Eq": "0",
      "Total Non Current Assets": "40.96",
      "Total Current Assets": "60.55",
      "Total Assets": "98.61",
      "Net Working Capital": "38.22",
      "Net Invested Capital": "24.23",
      "Common Share Oustanding": "1.03",
      "Book Value / Share": "23.62"
    },
    {
      "Date": "Mar-19",
      "Total Stockholders Fund": "82.02",
      "Minority Interest": "0.111",
      "Total Non Current Liabilities": "0.553",
      "Total Current Liabilities": "0.0288",
      "Total Liabilities": "21.05",
      "Liabilities & Sh Holder Eq": "0",
      "Total Non Current Assets": "41.34",
      "Total Current Assets": "60.84",
      "Total Assets": "103.07",
      "Net Working Capital": "41.23",
      "Net Invested Capital": "15.62",
      "Common Share Oustanding": "1.03",
      "Book Value / Share": "79.95"
    },
    {
      "Date": "Mar-18",
      "Total Stockholders Fund": "81.85",
      "Minority Interest": "1.49",
      "Total Non Current Liabilities": "0.0247",
      "Total Current Liabilities": "19.60",
      "Total Liabilities": "19.63",
      "Liabilities & Sh Holder Eq": "0",
      "Total Non Current Assets": "43.25",
      "Total Current Assets": "58.22",
      "Total Assets": "101.48",
      "Net Working Capital": "38.62",
      "Net Invested Capital": "15.45",
      "Common Share Oustanding": "1.03",
      "Book Value / Share": "79.79"
    },
    {
      "Date": "Mar-17",
      "Total Stockholders Fund": "98.30",
      "Minority Interest": "0",
      "Total Non Current Liabilities": "0.0118",
      "Total Current Liabilities": "19.57",
      "Total Liabilities": "19.58",
      "Liabilities & Sh Holder Eq": "0",
      "Total Non Current Assets": "59.88",
      "Total Current Assets": "58.00",
      "Total Assets": "117.88",
      "Net Working Capital": "-28.48",
      "Net Invested Capital": "0",
      "Common Share Oustanding": "1.03",
      "Book Value / Share": "95.83"
    },
    {
      "Date": "Mar-16",
      "Total Stockholders Fund": "-76.24",
      "Minority Interest": "1178.28",
      "Total Non Current Liabilities": "5795.89",
      "Total Current Liabilities": "1255.40",
      "Total Liabilities": "6582.65",
      "Liabilities & Sh Holder Eq": "0",
      "Total Non Current Assets": "6895.86",
      "Total Current Assets": "489.85",
      "Total Assets": "7732.09",
      "Net Working Capital": "-1176.21",
      "Net Invested Capital": "0",
      "Common Share Oustanding": "1.03",
      "Book Value / Share": "1120.31"
    },
    {
      "Date": "Mar-15",
      "Total Stockholders Fund": "134.91",
      "Minority Interest": "1049.15",
      "Total Non Current Liabilities": "5384.31",
      "Total Current Liabilities": "1489.98",
      "Total Liabilities": "5982.27",
      "Liabilities & Sh Holder Eq": "0",
      "Total Non Current Assets": "6824.01",
      "Total Current Assets": "354.08",
      "Total Assets": "7213.73",
      "Net Working Capital": "-1172.36",
      "Net Invested Capital": "0",
      "Common Share Oustanding": "1.03",
      "Book Value / Share": "1195.59"
    },
    {
      "Date": "Mar-14",
      "Total Stockholders Fund": "230.75",
      "Minority Interest": "751.98",
      "Total Non Current Liabilities": "4314.56",
      "Total Current Liabilities": "705.53",
      "Total Liabilities": "4968.04",
      "Liabilities & Sh Holder Eq": "0",
      "Total Non Current Assets": "5830.31",
      "Total Current Assets": "361.04",
      "Total Assets": "6098.17",
      "Net Working Capital": "-1237.60",
      "Net Invested Capital": "0",
      "Common Share Oustanding": "1.03",
      "Book Value / Share": "1101.71"
    },
    {
      "Date": "Mar-13",
      "Total Stockholders Fund": "247.83",
      "Minority Interest": "-23.42",
      "Total Non Current Liabilities": "3401.63",
      "Total Current Liabilities": "961.04",
      "Total Liabilities": "4362.67",
      "Liabilities & Sh Holder Eq": "0",
      "Total Non Current Assets": "4330.95",
      "Total Current Assets": "279.55",
      "Total Assets": "4610.50",
      "Net Working Capital": "-681.49",
      "Net Invested Capital": "0",
      "Common Share Oustanding": "1.03",
      "Book Value / Share": "241.60"
    },
    {
      "Date": "Mar-12",
      "Total Stockholders Fund": "252.65",
      "Minority Interest": "2.02",
      "Total Non Current Liabilities": "1967.12",
      "Total Current Liabilities": "1011.89",
      "Total Liabilities": "2979.01",
      "Liabilities & Sh Holder Eq": "0",
      "Total Non Current Assets": "2845.91",
      "Total Current Assets": "385.75",
      "Total Assets": "3231.66",
      "Net Working Capital": "-626.14",
      "Net Invested Capital": "0",
      "Common Share Oustanding": "1.03",
      "Book Value / Share": "246.30"
    },
    {
      "Date": "Mar-11",
      "Total Stockholders Fund": "234.68",
      "Minority Interest": "0.160",
      "Total Non Current Liabilities": "0",
      "Total Current Liabilities": "74.27",
      "Total Liabilities": "74.27",
      "Liabilities & Sh Holder Eq": "0",
      "Total Non Current Assets": "186.74",
      "Total Current Assets": "122.21",
      "Total Assets": "308.95",
      "Net Working Capital": "47.94",
      "Net Invested Capital": "0",
      "Common Share Oustanding": "1.03",
      "Book Value / Share": "228.78"
    },
    {
      "Date": "Mar-10",
      "Total Stockholders Fund": "217.98",
      "Minority Interest": "-0.110",
      "Total Non Current Liabilities": "1.85",
      "Total Current Liabilities": "43.44",
      "Total Liabilities": "45.29",
      "Liabilities & Sh Holder Eq": "0",
      "Total Non Current Assets": "138.44",
      "Total Current Assets": "124.83",
      "Total Assets": "263.27",
      "Net Working Capital": "81.39",
      "Net Invested Capital": "0",
      "Common Share Oustanding": "1.03",
      "Book Value / Share": "212.50"
    },
    {
      "Date": "Mar-09",
      "Total Stockholders Fund": "204.86",
      "Minority Interest": "-0.070",
      "Total Non Current Liabilities": "45.40",
      "Total Current Liabilities": "34.29",
      "Total Liabilities": "79.69",
      "Liabilities & Sh Holder Eq": "0",
      "Total Non Current Assets": "147.57",
      "Total Current Assets": "136.98",
      "Total Assets": "284.55",
      "Net Working Capital": "102.69",
      "Net Invested Capital": "0",
      "Common Share Oustanding": "1.03",
      "Book Value / Share": "199.71"
    },
    {
      "Date": "Mar-08",
      "Total Stockholders Fund": "176.61",
      "Minority Interest": "0.440",
      "Total Non Current Liabilities": "0",
      "Total Current Liabilities": "127.88",
      "Total Liabilities": "127.88",
      "Liabilities & Sh Holder Eq": "0",
      "Total Non Current Assets": "129.93",
      "Total Current Assets": "174.56",
      "Total Assets": "304.49",
      "Net Working Capital": "46.68",
      "Net Invested Capital": "0",
      "Common Share Oustanding": "1.03",
      "Book Value / Share": "172.17"
    },
    {
      "Date": "Mar-07",
      "Total Stockholders Fund": "133.91",
      "Minority Interest": "0.470",
      "Total Non Current Liabilities": "0",
      "Total Current Liabilities": "56.95",
      "Total Liabilities": "56.95",
      "Liabilities & Sh Holder Eq": "0",
      "Total Non Current Assets": "82.22",
      "Total Current Assets": "108.64",
      "Total Assets": "190.86",
      "Net Working Capital": "51.69",
      "Net Invested Capital": "0",
      "Common Share Oustanding": "1.03",
      "Book Value / Share": "130.54"
    },
    {
      "Date": "Mar-06",
      "Total Stockholders Fund": "104.87",
      "Minority Interest": "0",
      "Total Non Current Liabilities": "0",
      "Total Current Liabilities": "49.97",
      "Total Liabilities": "49.97",
      "Liabilities & Sh Holder Eq": "0",
      "Total Non Current Assets": "63.53",
      "Total Current Assets": "91.31",
      "Total Assets": "154.84",
      "Net Working Capital": "41.34",
      "Net Invested Capital": "0",
      "Common Share Oustanding": "1.03",
      "Book Value / Share": "102.23"
    },
    {
      "Date": "Mar-05",
      "Total Stockholders Fund": "86.59",
      "Minority Interest": "0",
      "Total Non Current Liabilities": "0.200",
      "Total Current Liabilities": "75.33",
      "Total Liabilities": "75.53",
      "Liabilities & Sh Holder Eq": "0",
      "Total Non Current Assets": "71.98",
      "Total Current Assets": "90.14",
      "Total Assets": "162.12",
      "Net Working Capital": "14.81",
      "Net Invested Capital": "0",
      "Common Share Oustanding": "1.03",
      "Book Value / Share": "84.41"
    }
  ],
  "IncomeStatement": [
    {
      "Date": "Mar-24",
      "Total Revenue/Income": "18.97",
      "Total Operating Expense": "0.090",
      "Operating Income/Profit": "18.87",
      "EBITDA": "99.57",
      "EBIT": "99.56",
      "Income/Profit Before Tax": "15.47",
      "Net Income From Continuing Operation": "15.47",
      "Net Income": "96.15",
      "Net Income Applicable to Common Share": "96.15",
      "EPS (Earning Per Share)": "93.72"
    },
    {
      "Date": "Dec-23",
      "Total Revenue/Income": "0.430",
      "Total Operating Expense": "0.090",
      "Operating Income/Profit": "0.320",
      "EBITDA": "90.43",
      "EBIT": "90.41",
      "Income/Profit Before Tax": "-0.0400",
      "Net Income From Continuing Operation": "-0.0400",
      "Net Income": "90.05",
      "Net Income Applicable to Common Share": "90.05",
      "EPS (Earning Per Share)": "87.77"
    },
    {
      "Date": "Sep-23",
      "Total Revenue/Income": "0.450",
      "Total Operating Expense": "0.140",
      "Operating Income/Profit": "0.300",
      "EBITDA": "45.82",
      "EBIT": "45.81",
      "Income/Profit Before Tax": "-0.070",
      "Net Income From Continuing Operation": "-0.070",
      "Net Income": "45.82",
      "Net Income Applicable to Common Share": "45.82",
      "EPS (Earning Per Share)": "44.67"
    },
    {
      "Date": "Jun-23",
      "Total Revenue/Income": "0.450",
      "Total Operating Expense": "0.120",
      "Operating Income/Profit": "0.320",
      "EBITDA": "33.90",
      "EBIT": "33.89",
      "Income/Profit Before Tax": "-0.0300",
      "Net Income From Continuing Operation": "-0.0300",
      "Net Income": "33.53",
      "Net Income Applicable to Common Share": "33.53",
      "EPS (Earning Per Share)": "32.69"
    },
    {
      "Date": "Mar-23",
      "Total Revenue/Income": "7.78",
      "Total Operating Expense": "0.120",
      "Operating Income/Profit": "7.65",
      "EBITDA": "53.18",
      "EBIT": "53.17",
      "Income/Profit Before Tax": "6.25",
      "Net Income From Continuing Operation": "6.39",
      "Net Income": "51.91",
      "Net Income Applicable to Common Share": "51.91",
      "EPS (Earning Per Share)": "50.59"
    },
    {
      "Date": "Dec-22",
      "Total Revenue/Income": "0.0400",
      "Total Operating Expense": "0.050",
      "Operating Income/Profit": "-0.100",
      "EBITDA": "43.66",
      "EBIT": "43.64",
      "Income/Profit Before Tax": "42.23",
      "Net Income From Continuing Operation": "42.59",
      "Net Income": "42.59",
      "Net Income Applicable to Common Share": "42.59",
      "EPS (Earning Per Share)": "0"
    },
    {
      "Date": "Sep-22",
      "Total Revenue/Income": "0.0400",
      "Total Operating Expense": "0.120",
      "Operating Income/Profit": "-0.080",
      "EBITDA": "-0.080",
      "EBIT": "-0.090",
      "Income/Profit Before Tax": "-1.50",
      "Net Income From Continuing Operation": "-1.12",
      "Net Income": "22.54",
      "Net Income Applicable to Common Share": "22.54",
      "EPS (Earning Per Share)": "21.97"
    },
    {
      "Date": "Jun-22",
      "Total Revenue/Income": "0.0100",
      "Total Operating Expense": "0.160",
      "Operating Income/Profit": "-0.160",
      "EBITDA": "51.29",
      "EBIT": "51.28",
      "Income/Profit Before Tax": "49.87",
      "Net Income From Continuing Operation": "50.12",
      "Net Income": "50.12",
      "Net Income Applicable to Common Share": "50.12",
      "EPS (Earning Per Share)": "48.85"
    },
    {
      "Date": "Mar-22",
      "Total Revenue/Income": "0.0100",
      "Total Operating Expense": "0.060",
      "Operating Income/Profit": "-0.060",
      "EBITDA": "84.98",
      "EBIT": "84.93",
      "Income/Profit Before Tax": "83.68",
      "Net Income From Continuing Operation": "84.11",
      "Net Income": "84.11",
      "Net Income Applicable to Common Share": "84.10",
      "EPS (Earning Per Share)": "81.98"
    },
    {
      "Date": "Dec-21",
      "Total Revenue/Income": "0.0200",
      "Total Operating Expense": "0.130",
      "Operating Income/Profit": "-0.130",
      "EBITDA": "4.07",
      "EBIT": "4.05",
      "Income/Profit Before Tax": "2.75",
      "Net Income From Continuing Operation": "3.14",
      "Net Income": "3.14",
      "Net Income Applicable to Common Share": "3.14",
      "EPS (Earning Per Share)": "3.06"
    },
    {
      "Date": "Sep-21",
      "Total Revenue/Income": "0.0400",
      "Total Operating Expense": "0.0400",
      "Operating Income/Profit": "-0.090",
      "EBITDA": "256.05",
      "EBIT": "256.03",
      "Income/Profit Before Tax": "-1.33",
      "Net Income From Continuing Operation": "255.06",
      "Net Income": "255.06",
      "Net Income Applicable to Common Share": "255.06",
      "EPS (Earning Per Share)": "248.64"
    },
    {
      "Date": "Jun-21",
      "Total Revenue/Income": "0.0200",
      "Total Operating Expense": "0.150",
      "Operating Income/Profit": "-0.130",
      "EBITDA": "292.37",
      "EBIT": "292.36",
      "Income/Profit Before Tax": "-1.42",
      "Net Income From Continuing Operation": "291.41",
      "Net Income": "291.41",
      "Net Income Applicable to Common Share": "291.41",
      "EPS (Earning Per Share)": "0"
    },
    {
      "Date": "Mar-21",
      "Total Revenue/Income": "0.110",
      "Total Operating Expense": "0.130",
      "Operating Income/Profit": "-0.0200",
      "EBITDA": "-0.0019",
      "EBIT": "-0.050",
      "Income/Profit Before Tax": "-1.20",
      "Net Income From Continuing Operation": "-1.45",
      "Net Income": "-1.45",
      "Net Income Applicable to Common Share": "-1.45",
      "EPS (Earning Per Share)": "-1.41"
    },
    {
      "Date": "Dec-20",
      "Total Revenue/Income": "0.0200",
      "Total Operating Expense": "0.070",
      "Operating Income/Profit": "-0.050",
      "EBITDA": "-0.0300",
      "EBIT": "-0.0300",
      "Income/Profit Before Tax": "-1.24",
      "Net Income From Continuing Operation": "-0.940",
      "Net Income": "-0.940",
      "Net Income Applicable to Common Share": "-0.940",
      "EPS (Earning Per Share)": "0"
    },
    {
      "Date": "Sep-20",
      "Total Revenue/Income": "0.0300",
      "Total Operating Expense": "0.070",
      "Operating Income/Profit": "-0.050",
      "EBITDA": "-0.080",
      "EBIT": "-0.100",
      "Income/Profit Before Tax": "-1.27",
      "Net Income From Continuing Operation": "-0.970",
      "Net Income": "-0.970",
      "Net Income Applicable to Common Share": "-0.970",
      "EPS (Earning Per Share)": "-0.946"
    },
    {
      "Date": "Jun-20",
      "Total Revenue/Income": "0.0400",
      "Total Operating Expense": "0.160",
      "Operating Income/Profit": "-0.120",
      "EBITDA": "0.0200",
      "EBIT": "0.0200",
      "Income/Profit Before Tax": "-1.18",
      "Net Income From Continuing Operation": "-1.11",
      "Net Income": "-1.11",
      "Net Income Applicable to Common Share": "-1.11",
      "EPS (Earning Per Share)": "0"
    },
    {
      "Date": "Mar-20",
      "Total Revenue/Income": "0.098",
      "Total Operating Expense": "0.241",
      "Operating Income/Profit": "-0.0409",
      "EBITDA": "-0.162",
      "EBIT": "-0.210",
      "Income/Profit Before Tax": "-1.08",
      "Net Income From Continuing Operation": "-0.506",
      "Net Income": "-0.506",
      "Net Income Applicable to Common Share": "-0.506",
      "EPS (Earning Per Share)": "-0.493"
    },
    {
      "Date": "Dec-19",
      "Total Revenue/Income": "0",
      "Total Operating Expense": "0.0300",
      "Operating Income/Profit": "-0.100",
      "EBITDA": "-0.050",
      "EBIT": "-0.0300",
      "Income/Profit Before Tax": "-1.19",
      "Net Income From Continuing Operation": "-0.880",
      "Net Income": "-0.880",
      "Net Income Applicable to Common Share": "-0.880",
      "EPS (Earning Per Share)": "0"
    },
    {
      "Date": "Sep-19",
      "Total Revenue/Income": "0",
      "Total Operating Expense": "0.080",
      "Operating Income/Profit": "-0.160",
      "EBITDA": "-0.090",
      "EBIT": "-0.080",
      "Income/Profit Before Tax": "-1.24",
      "Net Income From Continuing Operation": "-1.02",
      "Net Income": "-1.02",
      "Net Income Applicable to Common Share": "-1.02",
      "EPS (Earning Per Share)": "0"
    },
    {
      "Date": "Jun-19",
      "Total Revenue/Income": "0.0050",
      "Total Operating Expense": "0.135",
      "Operating Income/Profit": "-0.110",
      "EBITDA": "-2.38",
      "EBIT": "-0.130",
      "Income/Profit Before Tax": "-1.21",
      "Net Income From Continuing Operation": "-1.00",
      "Net Income": "-0.990",
      "Net Income Applicable to Common Share": "-0.990",
      "EPS (Earning Per Share)": "0"
    },
    {
      "Date": "Mar-19",
      "Total Revenue/Income": "0.070",
      "Total Operating Expense": "0.635",
      "Operating Income/Profit": "-0.890",
      "EBITDA": "-3.41",
      "EBIT": "1.85",
      "Income/Profit Before Tax": "0.800",
      "Net Income From Continuing Operation": "2.79",
      "Net Income": "-0.410",
      "Net Income Applicable to Common Share": "-0.410",
      "EPS (Earning Per Share)": "0"
    },
    {
      "Date": "Dec-18",
      "Total Revenue/Income": "0.160",
      "Total Operating Expense": "0.280",
      "Operating Income/Profit": "-0.120",
      "EBITDA": "-2.13",
      "EBIT": "-0.120",
      "Income/Profit Before Tax": "-1.13",
      "Net Income From Continuing Operation": "-0.920",
      "Net Income": "-0.920",
      "Net Income Applicable to Common Share": "-0.920",
      "EPS (Earning Per Share)": "0"
    },
    {
      "Date": "Sep-18",
      "Total Revenue/Income": "0.150",
      "Total Operating Expense": "0.170",
      "Operating Income/Profit": "-0.0200",
      "EBITDA": "-2.08",
      "EBIT": "-0.0200",
      "Income/Profit Before Tax": "-1.08",
      "Net Income From Continuing Operation": "-0.860",
      "Net Income": "-0.860",
      "Net Income Applicable to Common Share": "-0.860",
      "EPS (Earning Per Share)": "0"
    },
    {
      "Date": "Jun-18",
      "Total Revenue/Income": "0.150",
      "Total Operating Expense": "0.140",
      "Operating Income/Profit": "0.0100",
      "EBITDA": "-2.00",
      "EBIT": "0.0100",
      "Income/Profit Before Tax": "-0.995",
      "Net Income From Continuing Operation": "-0.795",
      "Net Income": "-0.795",
      "Net Income Applicable to Common Share": "-0.795",
      "EPS (Earning Per Share)": "0"
    },
    {
      "Date": "Mar-18",
      "Total Revenue/Income": "0",
      "Total Operating Expense": "0",
      "Operating Income/Profit": "0",
      "EBITDA": "0",
      "EBIT": "0",
      "Income/Profit Before Tax": "0",
      "Net Income From Continuing Operation": "0",
      "Net Income": "0",
      "Net Income Applicable to Common Share": "0",
      "EPS (Earning Per Share)": "0"
    },
    {
      "Date": "Dec-17",
      "Total Revenue/Income": "0.150",
      "Total Operating Expense": "0.110",
      "Operating Income/Profit": "0.0400",
      "EBITDA": "0.0400",
      "EBIT": "0.0400",
      "Income/Profit Before Tax": "0.0400",
      "Net Income From Continuing Operation": "0.0200",
      "Net Income": "0.0200",
      "Net Income Applicable to Common Share": "0.0200",
      "EPS (Earning Per Share)": "0"
    },
    {
      "Date": "Jun-17",
      "Total Revenue/Income": "0",
      "Total Operating Expense": "0",
      "Operating Income/Profit": "0",
      "EBITDA": "0",
      "EBIT": "0",
      "Income/Profit Before Tax": "0",
      "Net Income From Continuing Operation": "0",
      "Net Income": "0",
      "Net Income Applicable to Common Share": "0",
      "EPS (Earning Per Share)": "0"
    },
    {
      "Date": "Mar-17",
      "Total Revenue/Income": "0",
      "Total Operating Expense": "0",
      "Operating Income/Profit": "0",
      "EBITDA": "0",
      "EBIT": "0",
      "Income/Profit Before Tax": "0",
      "Net Income From Continuing Operation": "0",
      "Net Income": "0",
      "Net Income Applicable to Common Share": "0",
      "EPS (Earning Per Share)": "0"
    },
    {
      "Date": "Dec-16",
      "Total Revenue/Income": "4.19",
      "Total Operating Expense": "0.120",
      "Operating Income/Profit": "4.07",
      "EBITDA": "4.05",
      "EBIT": "4.07",
      "Income/Profit Before Tax": "4.06",
      "Net Income From Continuing Operation": "3.76",
      "Net Income": "3.76",
      "Net Income Applicable to Common Share": "3.76",
      "EPS (Earning Per Share)": "0"
    },
    {
      "Date": "Jun-16",
      "Total Revenue/Income": "0",
      "Total Operating Expense": "0",
      "Operating Income/Profit": "0",
      "EBITDA": "0",
      "EBIT": "0",
      "Income/Profit Before Tax": "0",
      "Net Income From Continuing Operation": "0",
      "Net Income": "0",
      "Net Income Applicable to Common Share": "0",
      "EPS (Earning Per Share)": "0"
    },
    {
      "Date": "Mar-16",
      "Total Revenue/Income": "0",
      "Total Operating Expense": "0",
      "Operating Income/Profit": "0",
      "EBITDA": "0",
      "EBIT": "0",
      "Income/Profit Before Tax": "0",
      "Net Income From Continuing Operation": "0",
      "Net Income": "0",
      "Net Income Applicable to Common Share": "0",
      "EPS (Earning Per Share)": "0"
    },
    {
      "Date": "Dec-15",
      "Total Revenue/Income": "0",
      "Total Operating Expense": "0",
      "Operating Income/Profit": "0",
      "EBITDA": "0",
      "EBIT": "0",
      "Income/Profit Before Tax": "0",
      "Net Income From Continuing Operation": "0",
      "Net Income": "0",
      "Net Income Applicable to Common Share": "0",
      "EPS (Earning Per Share)": "0"
    },
    {
      "Date": "Sep-15",
      "Total Revenue/Income": "0",
      "Total Operating Expense": "0",
      "Operating Income/Profit": "0",
      "EBITDA": "0",
      "EBIT": "0",
      "Income/Profit Before Tax": "0",
      "Net Income From Continuing Operation": "0",
      "Net Income": "0",
      "Net Income Applicable to Common Share": "0",
      "EPS (Earning Per Share)": "0"
    },
    {
      "Date": "Jun-15",
      "Total Revenue/Income": "0",
      "Total Operating Expense": "0",
      "Operating Income/Profit": "0",
      "EBITDA": "0",
      "EBIT": "0",
      "Income/Profit Before Tax": "0",
      "Net Income From Continuing Operation": "0",
      "Net Income": "0",
      "Net Income Applicable to Common Share": "0",
      "EPS (Earning Per Share)": "0"
    },
    {
      "Date": "Mar-15",
      "Total Revenue/Income": "0",
      "Total Operating Expense": "0",
      "Operating Income/Profit": "0",
      "EBITDA": "0",
      "EBIT": "0",
      "Income/Profit Before Tax": "0",
      "Net Income From Continuing Operation": "0",
      "Net Income": "0",
      "Net Income Applicable to Common Share": "0",
      "EPS (Earning Per Share)": "0"
    },
    {
      "Date": "Dec-14",
      "Total Revenue/Income": "0",
      "Total Operating Expense": "0",
      "Operating Income/Profit": "0",
      "EBITDA": "0",
      "EBIT": "0",
      "Income/Profit Before Tax": "0",
      "Net Income From Continuing Operation": "0",
      "Net Income": "0",
      "Net Income Applicable to Common Share": "0",
      "EPS (Earning Per Share)": "0"
    },
    {
      "Date": "Sep-14",
      "Total Revenue/Income": "0",
      "Total Operating Expense": "0",
      "Operating Income/Profit": "0",
      "EBITDA": "0",
      "EBIT": "0",
      "Income/Profit Before Tax": "0",
      "Net Income From Continuing Operation": "0",
      "Net Income": "0",
      "Net Income Applicable to Common Share": "0",
      "EPS (Earning Per Share)": "0"
    },
    {
      "Date": "Jun-14",
      "Total Revenue/Income": "0",
      "Total Operating Expense": "0",
      "Operating Income/Profit": "0",
      "EBITDA": "0",
      "EBIT": "0",
      "Income/Profit Before Tax": "0",
      "Net Income From Continuing Operation": "0",
      "Net Income": "0",
      "Net Income Applicable to Common Share": "0",
      "EPS (Earning Per Share)": "0"
    },
    {
      "Date": "Mar-14",
      "Total Revenue/Income": "0",
      "Total Operating Expense": "0",
      "Operating Income/Profit": "0",
      "EBITDA": "0",
      "EBIT": "0",
      "Income/Profit Before Tax": "0",
      "Net Income From Continuing Operation": "0",
      "Net Income": "0",
      "Net Income Applicable to Common Share": "0",
      "EPS (Earning Per Share)": "0"
    },
    {
      "Date": "Dec-13",
      "Total Revenue/Income": "0",
      "Total Operating Expense": "0",
      "Operating Income/Profit": "0",
      "EBITDA": "0",
      "EBIT": "0",
      "Income/Profit Before Tax": "0",
      "Net Income From Continuing Operation": "0",
      "Net Income": "0",
      "Net Income Applicable to Common Share": "0",
      "EPS (Earning Per Share)": "0"
    },
    {
      "Date": "Sep-13",
      "Total Revenue/Income": "0",
      "Total Operating Expense": "0",
      "Operating Income/Profit": "0",
      "EBITDA": "0",
      "EBIT": "0",
      "Income/Profit Before Tax": "0",
      "Net Income From Continuing Operation": "0",
      "Net Income": "0",
      "Net Income Applicable to Common Share": "0",
      "EPS (Earning Per Share)": "0"
    },
    {
      "Date": "Jun-13",
      "Total Revenue/Income": "0",
      "Total Operating Expense": "0",
      "Operating Income/Profit": "0",
      "EBITDA": "0",
      "EBIT": "0",
      "Income/Profit Before Tax": "0",
      "Net Income From Continuing Operation": "0",
      "Net Income": "0",
      "Net Income Applicable to Common Share": "0",
      "EPS (Earning Per Share)": "0"
    },
    {
      "Date": "Mar-13",
      "Total Revenue/Income": "93.80",
      "Total Operating Expense": "12.44",
      "Operating Income/Profit": "-1.65",
      "EBITDA": "-14.72",
      "EBIT": "-15.16",
      "Income/Profit Before Tax": "-38.87",
      "Net Income From Continuing Operation": "0",
      "Net Income": "-16.10",
      "Net Income Applicable to Common Share": "0",
      "EPS (Earning Per Share)": "-15.77"
    },
    {
      "Date": "Dec-12",
      "Total Revenue/Income": "118.70",
      "Total Operating Expense": "11.79",
      "Operating Income/Profit": "6.61",
      "EBITDA": "7.06",
      "EBIT": "6.61",
      "Income/Profit Before Tax": "5.40",
      "Net Income From Continuing Operation": "0",
      "Net Income": "4.18",
      "Net Income Applicable to Common Share": "0",
      "EPS (Earning Per Share)": "0"
    },
    {
      "Date": "Sep-12",
      "Total Revenue/Income": "126.25",
      "Total Operating Expense": "12.53",
      "Operating Income/Profit": "2.30",
      "EBITDA": "2.75",
      "EBIT": "2.30",
      "Income/Profit Before Tax": "1.19",
      "Net Income From Continuing Operation": "0",
      "Net Income": "0.330",
      "Net Income Applicable to Common Share": "0",
      "EPS (Earning Per Share)": "0.322"
    },
    {
      "Date": "Jun-12",
      "Total Revenue/Income": "131.23",
      "Total Operating Expense": "13.85",
      "Operating Income/Profit": "1.99",
      "EBITDA": "2.44",
      "EBIT": "1.99",
      "Income/Profit Before Tax": "0.970",
      "Net Income From Continuing Operation": "0",
      "Net Income": "0.990",
      "Net Income Applicable to Common Share": "0",
      "EPS (Earning Per Share)": "0"
    },
    {
      "Date": "Mar-12",
      "Total Revenue/Income": "0",
      "Total Operating Expense": "0",
      "Operating Income/Profit": "0",
      "EBITDA": "0",
      "EBIT": "0",
      "Income/Profit Before Tax": "0",
      "Net Income From Continuing Operation": "0",
      "Net Income": "0",
      "Net Income Applicable to Common Share": "0",
      "EPS (Earning Per Share)": "0"
    },
    {
      "Date": "Dec-11",
      "Total Revenue/Income": "0",
      "Total Operating Expense": "0",
      "Operating Income/Profit": "0",
      "EBITDA": "0",
      "EBIT": "0",
      "Income/Profit Before Tax": "0",
      "Net Income From Continuing Operation": "0",
      "Net Income": "0",
      "Net Income Applicable to Common Share": "0",
      "EPS (Earning Per Share)": "0"
    },
    {
      "Date": "Sep-11",
      "Total Revenue/Income": "0",
      "Total Operating Expense": "0",
      "Operating Income/Profit": "0",
      "EBITDA": "0",
      "EBIT": "0",
      "Income/Profit Before Tax": "0",
      "Net Income From Continuing Operation": "0",
      "Net Income": "0",
      "Net Income Applicable to Common Share": "0",
      "EPS (Earning Per Share)": "0"
    },
    {
      "Date": "Jun-11",
      "Total Revenue/Income": "0",
      "Total Operating Expense": "0",
      "Operating Income/Profit": "0",
      "EBITDA": "0",
      "EBIT": "0",
      "Income/Profit Before Tax": "0",
      "Net Income From Continuing Operation": "0",
      "Net Income": "0",
      "Net Income Applicable to Common Share": "0",
      "EPS (Earning Per Share)": "0"
    },
    {
      "Date": "Mar-11",
      "Total Revenue/Income": "0",
      "Total Operating Expense": "0",
      "Operating Income/Profit": "0",
      "EBITDA": "0",
      "EBIT": "0",
      "Income/Profit Before Tax": "0",
      "Net Income From Continuing Operation": "0",
      "Net Income": "0",
      "Net Income Applicable to Common Share": "0",
      "EPS (Earning Per Share)": "0"
    },
    {
      "Date": "Dec-10",
      "Total Revenue/Income": "0",
      "Total Operating Expense": "0",
      "Operating Income/Profit": "0",
      "EBITDA": "0",
      "EBIT": "0",
      "Income/Profit Before Tax": "0",
      "Net Income From Continuing Operation": "0",
      "Net Income": "0",
      "Net Income Applicable to Common Share": "0",
      "EPS (Earning Per Share)": "0"
    },
    {
      "Date": "Sep-10",
      "Total Revenue/Income": "0",
      "Total Operating Expense": "0",
      "Operating Income/Profit": "0",
      "EBITDA": "0",
      "EBIT": "0",
      "Income/Profit Before Tax": "0",
      "Net Income From Continuing Operation": "0",
      "Net Income": "0",
      "Net Income Applicable to Common Share": "0",
      "EPS (Earning Per Share)": "0"
    },
    {
      "Date": "Jun-10",
      "Total Revenue/Income": "0",
      "Total Operating Expense": "0",
      "Operating Income/Profit": "0",
      "EBITDA": "0",
      "EBIT": "0",
      "Income/Profit Before Tax": "0",
      "Net Income From Continuing Operation": "0",
      "Net Income": "0",
      "Net Income Applicable to Common Share": "0",
      "EPS (Earning Per Share)": "0"
    },
    {
      "Date": "Mar-10",
      "Total Revenue/Income": "0",
      "Total Operating Expense": "0",
      "Operating Income/Profit": "0",
      "EBITDA": "0",
      "EBIT": "0",
      "Income/Profit Before Tax": "0",
      "Net Income From Continuing Operation": "0",
      "Net Income": "0",
      "Net Income Applicable to Common Share": "0",
      "EPS (Earning Per Share)": "0"
    },
    {
      "Date": "Dec-09",
      "Total Revenue/Income": "0",
      "Total Operating Expense": "0",
      "Operating Income/Profit": "0",
      "EBITDA": "0",
      "EBIT": "0",
      "Income/Profit Before Tax": "0",
      "Net Income From Continuing Operation": "0",
      "Net Income": "0",
      "Net Income Applicable to Common Share": "0",
      "EPS (Earning Per Share)": "0"
    },
    {
      "Date": "Sep-09",
      "Total Revenue/Income": "0",
      "Total Operating Expense": "0",
      "Operating Income/Profit": "0",
      "EBITDA": "0",
      "EBIT": "0",
      "Income/Profit Before Tax": "0",
      "Net Income From Continuing Operation": "0",
      "Net Income": "0",
      "Net Income Applicable to Common Share": "0",
      "EPS (Earning Per Share)": "0"
    },
    {
      "Date": "Jun-09",
      "Total Revenue/Income": "0",
      "Total Operating Expense": "0",
      "Operating Income/Profit": "0",
      "EBITDA": "0",
      "EBIT": "0",
      "Income/Profit Before Tax": "0",
      "Net Income From Continuing Operation": "0",
      "Net Income": "0",
      "Net Income Applicable to Common Share": "0",
      "EPS (Earning Per Share)": "0"
    },
    {
      "Date": "Mar-09",
      "Total Revenue/Income": "0",
      "Total Operating Expense": "0",
      "Operating Income/Profit": "0",
      "EBITDA": "0",
      "EBIT": "0",
      "Income/Profit Before Tax": "0",
      "Net Income From Continuing Operation": "0",
      "Net Income": "0",
      "Net Income Applicable to Common Share": "0",
      "EPS (Earning Per Share)": "0"
    },
    {
      "Date": "Dec-08",
      "Total Revenue/Income": "0",
      "Total Operating Expense": "0",
      "Operating Income/Profit": "0",
      "EBITDA": "0",
      "EBIT": "0",
      "Income/Profit Before Tax": "0",
      "Net Income From Continuing Operation": "0",
      "Net Income": "0",
      "Net Income Applicable to Common Share": "0",
      "EPS (Earning Per Share)": "0"
    },
    {
      "Date": "Sep-08",
      "Total Revenue/Income": "0",
      "Total Operating Expense": "0",
      "Operating Income/Profit": "0",
      "EBITDA": "0",
      "EBIT": "0",
      "Income/Profit Before Tax": "0",
      "Net Income From Continuing Operation": "0",
      "Net Income": "0",
      "Net Income Applicable to Common Share": "0",
      "EPS (Earning Per Share)": "0"
    },
    {
      "Date": "Jun-08",
      "Total Revenue/Income": "0",
      "Total Operating Expense": "0",
      "Operating Income/Profit": "0",
      "EBITDA": "0",
      "EBIT": "0",
      "Income/Profit Before Tax": "0",
      "Net Income From Continuing Operation": "0",
      "Net Income": "0",
      "Net Income Applicable to Common Share": "0",
      "EPS (Earning Per Share)": "0"
    },
    {
      "Date": "Mar-08",
      "Total Revenue/Income": "0",
      "Total Operating Expense": "0",
      "Operating Income/Profit": "0",
      "EBITDA": "0",
      "EBIT": "0",
      "Income/Profit Before Tax": "0",
      "Net Income From Continuing Operation": "0",
      "Net Income": "0",
      "Net Income Applicable to Common Share": "0",
      "EPS (Earning Per Share)": "0"
    },
    {
      "Date": "Dec-07",
      "Total Revenue/Income": "0",
      "Total Operating Expense": "0",
      "Operating Income/Profit": "0",
      "EBITDA": "0",
      "EBIT": "0",
      "Income/Profit Before Tax": "0",
      "Net Income From Continuing Operation": "0",
      "Net Income": "0",
      "Net Income Applicable to Common Share": "0",
      "EPS (Earning Per Share)": "0"
    },
    {
      "Date": "Sep-07",
      "Total Revenue/Income": "0",
      "Total Operating Expense": "0",
      "Operating Income/Profit": "0",
      "EBITDA": "0",
      "EBIT": "0",
      "Income/Profit Before Tax": "0",
      "Net Income From Continuing Operation": "0",
      "Net Income": "0",
      "Net Income Applicable to Common Share": "0",
      "EPS (Earning Per Share)": "0"
    },
    {
      "Date": "Jun-07",
      "Total Revenue/Income": "0",
      "Total Operating Expense": "0",
      "Operating Income/Profit": "0",
      "EBITDA": "0",
      "EBIT": "0",
      "Income/Profit Before Tax": "0",
      "Net Income From Continuing Operation": "0",
      "Net Income": "0",
      "Net Income Applicable to Common Share": "0",
      "EPS (Earning Per Share)": "0"
    },
    {
      "Date": "Mar-07",
      "Total Revenue/Income": "0",
      "Total Operating Expense": "0",
      "Operating Income/Profit": "0",
      "EBITDA": "0",
      "EBIT": "0",
      "Income/Profit Before Tax": "0",
      "Net Income From Continuing Operation": "0",
      "Net Income": "0",
      "Net Income Applicable to Common Share": "0",
      "EPS (Earning Per Share)": "0"
    },
    {
      "Date": "Dec-06",
      "Total Revenue/Income": "0",
      "Total Operating Expense": "0",
      "Operating Income/Profit": "0",
      "EBITDA": "0",
      "EBIT": "0",
      "Income/Profit Before Tax": "0",
      "Net Income From Continuing Operation": "0",
      "Net Income": "0",
      "Net Income Applicable to Common Share": "0",
      "EPS (Earning Per Share)": "0"
    }
  ],
  "CashFlow": [
    {
      "Date": "Mar-24",
      "Net Income": "265.55",
      "Cash From Operating Activities": "-0.380",
      "Cash From Investing Activities": "0.390",
      "Cash from Financing Activities": "0",
      "Cash And Cash Equivalent Change": "0.0071",
      "Free Cash Flow": "-0.380"
    },
    {
      "Date": "Mar-23",
      "Net Income": "167.16",
      "Cash From Operating Activities": "-0.510",
      "Cash From Investing Activities": "0.500",
      "Cash from Financing Activities": "0",
      "Cash And Cash Equivalent Change": "-0.0100",
      "Free Cash Flow": "-0.510"
    },
    {
      "Date": "Mar-22",
      "Net Income": "633.72",
      "Cash From Operating Activities": "-0.170",
      "Cash From Investing Activities": "1.63",
      "Cash from Financing Activities": "0",
      "Cash And Cash Equivalent Change": "1.45",
      "Free Cash Flow": "-0.360"
    },
    {
      "Date": "Mar-21",
      "Net Income": "-4.46",
      "Cash From Operating Activities": "-3.08",
      "Cash From Investing Activities": "3.14",
      "Cash from Financing Activities": "0",
      "Cash And Cash Equivalent Change": "0.060",
      "Free Cash Flow": "-0.170"
    },
    {
      "Date": "Mar-20",
      "Net Income": "-3.40",
      "Cash From Operating Activities": "-0.430",
      "Cash From Investing Activities": "0.488",
      "Cash from Financing Activities": "0",
      "Cash And Cash Equivalent Change": "0.058",
      "Free Cash Flow": "-3.08"
    },
    {
      "Date": "Mar-19",
      "Net Income": "0.168",
      "Cash From Operating Activities": "-1.38",
      "Cash From Investing Activities": "1.31",
      "Cash from Financing Activities": "-0.0004",
      "Cash And Cash Equivalent Change": "-0.071",
      "Free Cash Flow": "1.70"
    },
    {
      "Date": "Mar-18",
      "Net Income": "-2.40",
      "Cash From Operating Activities": "0.166",
      "Cash From Investing Activities": "-0.153",
      "Cash from Financing Activities": "-0.0004",
      "Cash And Cash Equivalent Change": "0.0119",
      "Free Cash Flow": "0.166"
    },
    {
      "Date": "Mar-17",
      "Net Income": "-0.0420",
      "Cash From Operating Activities": "-4.06",
      "Cash From Investing Activities": "7.26",
      "Cash from Financing Activities": "-3.22",
      "Cash And Cash Equivalent Change": "-128.70",
      "Free Cash Flow": "-4.06"
    },
    {
      "Date": "Mar-16",
      "Net Income": "-211.15",
      "Cash From Operating Activities": "-257.69",
      "Cash From Investing Activities": "-348.13",
      "Cash from Financing Activities": "599.63",
      "Cash And Cash Equivalent Change": "-6.19",
      "Free Cash Flow": "-476.45"
    },
    {
      "Date": "Mar-15",
      "Net Income": "-30.80",
      "Cash From Operating Activities": "639.47",
      "Cash From Investing Activities": "-1053.14",
      "Cash from Financing Activities": "519.87",
      "Cash And Cash Equivalent Change": "106.63",
      "Free Cash Flow": "-476.79"
    },
    {
      "Date": "Mar-14",
      "Net Income": "-86.78",
      "Cash From Operating Activities": "162.57",
      "Cash From Investing Activities": "-1470.35",
      "Cash from Financing Activities": "1273.97",
      "Cash And Cash Equivalent Change": "-33.80",
      "Free Cash Flow": "-1331.81"
    },
    {
      "Date": "Mar-13",
      "Net Income": "-10.61",
      "Cash From Operating Activities": "-143.28",
      "Cash From Investing Activities": "-1480.94",
      "Cash from Financing Activities": "1530.82",
      "Cash And Cash Equivalent Change": "-93.40",
      "Free Cash Flow": "0"
    },
    {
      "Date": "Mar-12",
      "Net Income": "15.16",
      "Cash From Operating Activities": "668.64",
      "Cash From Investing Activities": "-1780.16",
      "Cash from Financing Activities": "1267.73",
      "Cash And Cash Equivalent Change": "156.21",
      "Free Cash Flow": "0"
    },
    {
      "Date": "Mar-11",
      "Net Income": "18.02",
      "Cash From Operating Activities": "45.84",
      "Cash From Investing Activities": "-49.17",
      "Cash from Financing Activities": "-3.13",
      "Cash And Cash Equivalent Change": "-6.46",
      "Free Cash Flow": "0"
    },
    {
      "Date": "Mar-10",
      "Net Income": "14.64",
      "Cash From Operating Activities": "3.43",
      "Cash From Investing Activities": "13.68",
      "Cash from Financing Activities": "-46.36",
      "Cash And Cash Equivalent Change": "-29.25",
      "Free Cash Flow": "0"
    },
    {
      "Date": "Mar-09",
      "Net Income": "29.44",
      "Cash From Operating Activities": "9.52",
      "Cash From Investing Activities": "-94.04",
      "Cash from Financing Activities": "41.55",
      "Cash And Cash Equivalent Change": "-42.97",
      "Free Cash Flow": "0"
    },
    {
      "Date": "Mar-08",
      "Net Income": "46.48",
      "Cash From Operating Activities": "46.48",
      "Cash From Investing Activities": "-53.58",
      "Cash from Financing Activities": "78.34",
      "Cash And Cash Equivalent Change": "71.24",
      "Free Cash Flow": "0"
    },
    {
      "Date": "Mar-07",
      "Net Income": "26.99",
      "Cash From Operating Activities": "24.07",
      "Cash From Investing Activities": "-19.31",
      "Cash from Financing Activities": "-2.01",
      "Cash And Cash Equivalent Change": "2.75",
      "Free Cash Flow": "0"
    },
    {
      "Date": "Mar-06",
      "Net Income": "19.46",
      "Cash From Operating Activities": "17.38",
      "Cash From Investing Activities": "7.62",
      "Cash from Financing Activities": "-21.41",
      "Cash And Cash Equivalent Change": "3.59",
      "Free Cash Flow": "0"
    },
    {
      "Date": "Mar-05",
      "Net Income": "28.51",
      "Cash From Operating Activities": "-31.20",
      "Cash From Investing Activities": "36.07",
      "Cash from Financing Activities": "-1.20",
      "Cash And Cash Equivalent Change": "3.67",
      "Free Cash Flow": "0"
    }
  ]
}